cipherlib/AES.py
cipherlib/ARIA.py
cipherlib/BaseCipher.py
cipherlib/Blowfish.py
cipherlib/CAST.py
cipherlib/Camellia.py
cipherlib/DES.py
cipherlib/DES3.py
cipherlib/IDEA.py
cipherlib/SM4.py
cipherlib/__init__.py
cipherlib-0.0.2.dist-info/METADATA
cipherlib-0.0.2.dist-info/WHEEL
cipherlib-0.0.2.dist-info/top_level.txt
cipherlib-0.0.2.dist-info/RECORD
